asynctranslator/__init__.py
asynctranslator/current_thread_executor.py
asynctranslator/local.py
asynctranslator/py.typed
asynctranslator/sync.py
LICENSE
LICENSE.django
asynctranslator-1.0.1.dist-info/LICENSE
asynctranslator-1.0.1.dist-info/LICENSE.django
asynctranslator-1.0.1.dist-info/WHEEL
asynctranslator-1.0.1.dist-info/METADATA
asynctranslator-1.0.1.dist-info/RECORD
